labbie/__init__.py
labbie/__main__.py
labbie/bases.py
labbie/bounds.py
labbie/config.py
labbie/constants.py
labbie/di/__init__.py
labbie/di/module.py
labbie/enchants.py
labbie/errors.py
labbie/mixins.py
labbie/mods.py
labbie/ocr.py
labbie/resources.py
labbie/result.py
labbie/state.py
labbie/trade.py
labbie/ui/__init__.py
labbie/ui/about/__init__.py
labbie/ui/about/widget/__init__.py
labbie/ui/about/widget/presenter.py
labbie/ui/about/widget/view.py
labbie/ui/about/window/__init__.py
labbie/ui/about/window/presenter.py
labbie/ui/about/window/view.py
labbie/ui/app/__init__.py
labbie/ui/app/presenter.py
labbie/ui/base.py
labbie/ui/checkable_combo.py
labbie/ui/clickable_label.py
labbie/ui/error/__init__.py
labbie/ui/error/widget/__init__.py
labbie/ui/error/widget/presenter.py
labbie/ui/error/widget/view.py
labbie/ui/error/window/__init__.py
labbie/ui/error/window/presenter.py
labbie/ui/error/window/view.py
labbie/ui/fuzzy_combo.py
labbie/ui/hotkey.py
labbie/ui/keys.py
labbie/ui/result/widget/__init__.py
labbie/ui/result/widget/presenter.py
labbie/ui/result/widget/view.py
labbie/ui/screen_selection/widget/__init__.py
labbie/ui/screen_selection/widget/view.py
labbie/ui/search/__init__.py
labbie/ui/search/widget/__init__.py
labbie/ui/search/widget/presenter.py
labbie/ui/search/widget/view.py
labbie/ui/search/window/__init__.py
labbie/ui/search/window/presenter.py
labbie/ui/search/window/view.py
labbie/ui/settings/__init__.py
labbie/ui/settings/widget/__init__.py
labbie/ui/settings/widget/presenter.py
labbie/ui/settings/widget/view.py
labbie/ui/settings/window/__init__.py
labbie/ui/settings/window/presenter.py
labbie/ui/settings/window/view.py
labbie/ui/switch.py
labbie/ui/system_tray/__init__.py
labbie/ui/system_tray/presenter.py
labbie/ui/system_tray/view.py
labbie/ui/transparent_window.py
labbie/ui/utils.py
labbie/utils.py
labbie/vendor/qtmodern/__init__.py
labbie/vendor/qtmodern/_utils.py
labbie/vendor/qtmodern/LICENSE
labbie/vendor/qtmodern/resources/frameless.qss
labbie-0.6.1.dist-info/entry_points.txt
labbie-0.6.1.dist-info/LICENSE
labbie-0.6.1.dist-info/WHEEL
labbie-0.6.1.dist-info/METADATA
labbie-0.6.1.dist-info/RECORD
