Metadata-Version: 2.1
Name: labbie
Version: 0.6.1
Summary: Lab enchant assistant
Author: Brandon Norick
Author-email: b.norick@gmail.com
Requires-Python: >=3.8,<3.9
Classifier: Programming Language :: Python :: 3
Classifier: Programming Language :: Python :: 3.8
Requires-Dist: Pillow (>=8.4.0,<9.0.0)
Requires-Dist: PyQt5 (>=5.15.6,<6.0.0)
Requires-Dist: aiohttp (>=3.8.0,<4.0.0)
Requires-Dist: dacite (>=1.6.0,<2.0.0)
Requires-Dist: datrie (>=0.8.2,<0.9.0)
Requires-Dist: injector (>=0.18.4,<0.19.0)
Requires-Dist: keyboard (>=0.13.5,<0.14.0)
Requires-Dist: loguru (>=0.5.3,<0.6.0)
Requires-Dist: numpy (>=1.21.4,<2.0.0)
Requires-Dist: opencv-python-headless (>=4.5.4,<5.0.0)
Requires-Dist: orjson (>=3.6.4,<4.0.0)
Requires-Dist: pyperclip (>=1.8.2,<2.0.0)
Requires-Dist: pytesseract (>=0.3.8,<0.4.0)
Requires-Dist: qasync (>=0.22.0,<0.23.0)
Requires-Dist: toml (>=0.10.2,<0.11.0)
